{
    "Objects": [
        {
            "name": "Land_Container_1Bo",
            "pos": [
                14228.19140625,
                -0.07881665229797363,
                13173.193359375
            ],
            "ypr": [
                -85.94757843017578,
                0.0,
                -34.999996185302737
            ],
            "scale": 0.9999983906745911,
            "enableCEPersistency": 0
        },
        {
            "name": "Land_Container_1Aoh",
            "pos": [
                14239.4853515625,
                -0.0003712177276611328,
                13169.5615234375
            ],
            "ypr": [
                -155.5506591796875,
                -4.999755382537842,
                -69.99999237060547
            ],
            "scale": 0.9999993443489075,
            "enableCEPersistency": 0
        },
        {
            "name": "Land_Container_1Mo",
            "pos": [
                14241.9833984375,
                -0.015660524368286134,
                13182.3876953125
            ],
            "ypr": [
                -15.759121894836426,
                0.0,
                -95.0
            ],
            "scale": 0.9999995231628418,
            "enableCEPersistency": 0
        },
        {
            "name": "StaticObj_Container_1D",
            "pos": [
                14255.5439453125,
                0.3123586177825928,
                13183.4794921875
            ],
            "ypr": [
                -171.3168182373047,
                0.0,
                -34.999996185302737
            ],
            "scale": 0.9999987483024597,
            "enableCEPersistency": 0
        },
        {
            "name": "StaticObj_Container_1C",
            "pos": [
                14258.2685546875,
                0.17388415336608888,
                13173.8408203125
            ],
            "ypr": [
                99.41065979003906,
                -19.9984073638916,
                -54.99993896484375
            ],
            "scale": 0.9999995231628418,
            "enableCEPersistency": 0
        },
        {
            "name": "Land_Container_1Bo",
            "pos": [
                14247.4921875,
                -0.05515027046203613,
                13175.640625
            ],
            "ypr": [
                -166.1568603515625,
                0.0,
                -46.99999237060547
            ],
            "scale": 1.0,
            "enableCEPersistency": 0
        },
        {
            "name": "Land_Container_1Aoh",
            "pos": [
                14259.8623046875,
                0.03936266899108887,
                13198.0087890625
            ],
            "ypr": [
                -69.60868072509766,
                -4.999617576599121,
                -69.99999237060547
            ],
            "scale": 0.999999463558197,
            "enableCEPersistency": 0
        },
        {
            "name": "Land_Container_1Mo",
            "pos": [
                14215.1103515625,
                0.5286662578582764,
                13178.544921875
            ],
            "ypr": [
                -163.7234649658203,
                0.0,
                -95.0
            ],
            "scale": 0.9999998807907105,
            "enableCEPersistency": 0
        },
        {
            "name": "StaticObj_Container_1C",
            "pos": [
                14236.71484375,
                -0.6607410907745361,
                13151.33203125
            ],
            "ypr": [
                -164.61312866210938,
                -19.992794036865236,
                -54.99996566772461
            ],
            "scale": 0.9999988675117493,
            "enableCEPersistency": 0
        },
        {
            "name": "StaticObj_Container_1D",
            "pos": [
                14219.958984375,
                -0.04317212104797363,
                13159.220703125
            ],
            "ypr": [
                167.4923553466797,
                0.0,
                -34.999996185302737
            ],
            "scale": 0.9999983906745911,
            "enableCEPersistency": 0
        },
        {
            "name": "Land_Container_1Mo",
            "pos": [
                14274.0927734375,
                -0.0014393329620361329,
                13184.9921875
            ],
            "ypr": [
                18.617698669433595,
                0.0,
                -95.0
            ],
            "scale": 0.9999997615814209,
            "enableCEPersistency": 0
        },
        {
            "name": "StaticObj_Rubble_Metal3",
            "pos": [
                14249.5458984375,
                0.18285632133483888,
                13167.0732421875
            ],
            "ypr": [
                -89.65760040283203,
                -0.0,
                -0.0
            ],
            "scale": 0.9999995231628418,
            "enableCEPersistency": 0
        },
        {
            "name": "StaticObj_Rubble_Metal3",
            "pos": [
                14232.8984375,
                0.39655566215515139,
                13181.353515625
            ],
            "ypr": [
                -168.01199340820313,
                -0.0,
                -0.0
            ],
            "scale": 0.9999999403953552,
            "enableCEPersistency": 0
        },
        {
            "name": "StaticObj_Furniture_metalcase_02",
            "pos": [
                14231.4287109375,
                0.46032214164733889,
                13159.744140625
            ],
            "ypr": [
                74.2852783203125,
                -82.97523498535156,
                -179.99989318847657
            ],
            "scale": 0.9999996423721314,
            "enableCEPersistency": 0
        },
        {
            "name": "StaticObj_Furniture_locker_open_v2",
            "pos": [
                14225.822265625,
                0.33678698539733889,
                13170.0869140625
            ],
            "ypr": [
                27.648752212524415,
                -76.98756408691406,
                0.0
            ],
            "scale": 1.0,
            "enableCEPersistency": 0
        },
        {
            "name": "StaticObj_Rubble_Metal3",
            "pos": [
                14213.5361328125,
                0.34832262992858889,
                13175.37109375
            ],
            "ypr": [
                102.13638305664063,
                -0.0,
                -0.0
            ],
            "scale": 0.9999996423721314,
            "enableCEPersistency": 0
        },
        {
            "name": "StaticObj_Furniture_locker_closed_v1",
            "pos": [
                14222.7626953125,
                0.40023303031921389,
                13177.525390625
            ],
            "ypr": [
                99.06682586669922,
                -79.99742889404297,
                179.99989318847657
            ],
            "scale": 1.0,
            "enableCEPersistency": 0
        },
        {
            "name": "StaticObj_ammoboxes_single",
            "pos": [
                14230.103515625,
                0.6524913311004639,
                13165.0859375
            ],
            "ypr": [
                -177.6158447265625,
                -24.999210357666017,
                0.0
            ],
            "scale": 0.9999992847442627,
            "enableCEPersistency": 0
        },
        {
            "name": "StaticObj_ammoboxes_single",
            "pos": [
                14219.81640625,
                0.45321154594421389,
                13173.17578125
            ],
            "ypr": [
                96.44175720214844,
                -24.999134063720704,
                45.99995040893555
            ],
            "scale": 0.9999997615814209,
            "enableCEPersistency": 0
        },
        {
            "name": "StaticObj_ammoboxes_single",
            "pos": [
                14228.7451171875,
                0.6454722881317139,
                13153.087890625
            ],
            "ypr": [
                -154.69790649414063,
                0.0,
                9.999996185302735
            ],
            "scale": 0.9999985694885254,
            "enableCEPersistency": 0
        },
        {
            "name": "StaticObj_ammoboxes_single",
            "pos": [
                14236.0517578125,
                0.8520572185516357,
                13159.53515625
            ],
            "ypr": [
                -57.296875,
                0.0,
                9.999996185302735
            ],
            "scale": 0.9999986886978149,
            "enableCEPersistency": 0
        },
        {
            "name": "StaticObj_ammoboxes_single",
            "pos": [
                14223.1689453125,
                0.7846286296844482,
                13165.9697265625
            ],
            "ypr": [
                -127.76851654052735,
                0.0,
                9.999996185302735
            ],
            "scale": 0.999998152256012,
            "enableCEPersistency": 0
        },
        {
            "name": "StaticObj_ammoboxes_single",
            "pos": [
                14213.359375,
                0.7576205730438232,
                13165.1669921875
            ],
            "ypr": [
                -104.85070037841797,
                0.0,
                9.999996185302735
            ],
            "scale": 0.9999983310699463,
            "enableCEPersistency": 0
        },
        {
            "name": "StaticObj_ammoboxes_single",
            "pos": [
                14236.44140625,
                0.6206920146942139,
                13180.4150390625
            ],
            "ypr": [
                -76.20333099365235,
                0.0,
                9.999996185302735
            ],
            "scale": 0.9999991059303284,
            "enableCEPersistency": 0
        },
        {
            "name": "StaticObj_ammoboxes_single",
            "pos": [
                14240.6669921875,
                0.7863528728485107,
                13175.3681640625
            ],
            "ypr": [
                18.904085159301759,
                0.0,
                9.999996185302735
            ],
            "scale": 0.9999980330467224,
            "enableCEPersistency": 0
        },
        {
            "name": "StaticObj_ammoboxes_single",
            "pos": [
                14233.6279296875,
                0.8136508464813232,
                13175.267578125
            ],
            "ypr": [
                70.46965789794922,
                0.0,
                9.999996185302735
            ],
            "scale": 0.9999992251396179,
            "enableCEPersistency": 0
        },
        {
            "name": "Land_Container_1Mo",
            "pos": [
                14245.28125,
                -0.09464097023010254,
                13157.35546875
            ],
            "ypr": [
                -67.32430267333985,
                0.0,
                -95.0
            ],
            "scale": 1.0,
            "enableCEPersistency": 0
        },
        {
            "name": "StaticObj_ammoboxes_single",
            "pos": [
                14252.869140625,
                0.6482493877410889,
                13189.9052734375
            ],
            "ypr": [
                -16.352556228637697,
                0.0,
                9.999996185302735
            ],
            "scale": 0.9999993443489075,
            "enableCEPersistency": 0
        },
        {
            "name": "StaticObj_ammoboxes_single",
            "pos": [
                14250.595703125,
                0.8138949871063232,
                13183.7392578125
            ],
            "ypr": [
                78.75932312011719,
                0.0,
                9.999996185302735
            ],
            "scale": 0.9999979734420776,
            "enableCEPersistency": 0
        },
        {
            "name": "StaticObj_ammoboxes_single",
            "pos": [
                14246.98828125,
                0.8411929607391357,
                13189.779296875
            ],
            "ypr": [
                130.32423400878907,
                0.0,
                9.999996185302735
            ],
            "scale": 0.9999991059303284,
            "enableCEPersistency": 0
        },
        {
            "name": "StaticObj_Wreck_Ship_Big_FrontA",
            "pos": [
                14283.6435546875,
                9.650639533996582,
                13151.9765625
            ],
            "ypr": [
                37.37889099121094,
                0.0,
                0.0
            ],
            "scale": 0.9999997615814209,
            "enableCEPersistency": 0
        },
        {
            "name": "StaticObj_Wreck_Ship_Big_FrontB",
            "pos": [
                14266.521484375,
                8.154240608215332,
                13162.275390625
            ],
            "ypr": [
                37.68655014038086,
                0.0,
                0.0
            ],
            "scale": 0.9999990463256836,
            "enableCEPersistency": 0
        },
        {
            "name": "StaticObj_Wreck_Ship_Big_BackB",
            "pos": [
                14221.1708984375,
                8.02422046661377,
                13221.146484375
            ],
            "ypr": [
                62.17251205444336,
                -0.0,
                -0.0
            ],
            "scale": 0.9999999403953552,
            "enableCEPersistency": 0
        },
        {
            "name": "StaticObj_Wreck_Ship_Big_BackA",
            "pos": [
                14229.7314453125,
                9.565068244934082,
                13203.4853515625
            ],
            "ypr": [
                62.351951599121097,
                0.0,
                0.0
            ],
            "scale": 0.9999997615814209,
            "enableCEPersistency": 0
        },
        {
            "name": "Land_Ship_Big_Castle",
            "pos": [
                14226.2490234375,
                18.23112678527832,
                13210.96875
            ],
            "ypr": [
                62.349822998046878,
                -0.0,
                -0.0
            ],
            "scale": 0.9999999403953552,
            "enableCEPersistency": 0
        }
    ]
}